robotframework_aci_cert_signed_requests/__init__.py
robotframework_aci_cert_signed_requests-0.1.2.dist-info/licenses/LICENSE
robotframework_aci_cert_signed_requests-0.1.2.dist-info/METADATA
robotframework_aci_cert_signed_requests-0.1.2.dist-info/WHEEL
robotframework_aci_cert_signed_requests-0.1.2.dist-info/top_level.txt
robotframework_aci_cert_signed_requests-0.1.2.dist-info/RECORD
