Metadata-Version: 2.4
Name: robotframework-aci-cert-signed-requests
Version: 0.1.2
Summary: Robot Framework library for sending certificate-signed requests to Cisco ACI
Author-email: Piotr Jasiński <pjasinsk@cisco.com>
License: MIT
Project-URL: Homepage, https://github.com/pjasinskcisco/robotframework-aci-cert-signed-requests
License-File: LICENSE
Requires-Dist: robotframework
Requires-Dist: cryptography
Requires-Dist: requests
Dynamic: license-file
